README.md
setup.py
triton/__init__.py
triton/query.py
triton/dns/__init__.py
triton/dns/edns.py
triton/dns/dnssec/__init__.py
triton/dns/dnssec/exceptions.py
triton/dns/dnssec/algorithms/__init__.py
triton/dns/dnssec/algorithms/base.py
triton/dns/dnssec/algorithms/dsa.py
triton/dns/dnssec/algorithms/ecc.py
triton/dns/dnssec/algorithms/ed.py
triton/dns/dnssec/algorithms/rsa.py
triton/dns/dnssec/digest/__init__.py
triton/dns/dnssec/digest/base.py
triton/dns/dnssec/digest/sha.py
triton/dns/message/__init__.py
triton/dns/message/answer.py
triton/dns/message/header.py
triton/dns/message/question.py
triton/dns/message/domains/__init__.py
triton/dns/message/domains/domain.py
triton/dns/message/domains/storage.py
triton/dns/message/rdata/__init__.py
triton/dns/message/rdata/a.py
triton/dns/message/rdata/aaaa.py
triton/dns/message/rdata/base.py
triton/dns/message/rdata/caa.py
triton/dns/message/rdata/cdnskey.py
triton/dns/message/rdata/cds.py
triton/dns/message/rdata/cname.py
triton/dns/message/rdata/dnskey.py
triton/dns/message/rdata/ds.py
triton/dns/message/rdata/key.py
triton/dns/message/rdata/mx.py
triton/dns/message/rdata/ns.py
triton/dns/message/rdata/nsec.py
triton/dns/message/rdata/opt.py
triton/dns/message/rdata/pointer.py
triton/dns/message/rdata/rrsig.py
triton/dns/message/rdata/soa.py
triton/dns/message/rdata/txt.py
triton/protocol/__init__.py
triton/protocol/exception.py
triton/protocol/tcp.py
triton/protocol/udp.py
triton/resolver/__init__.py
triton/resolver/connector.py
triton/resolver/exceptions.py
triton/resolver/local_cache.py
triton/resolver/resolver.py
triton/resolver/root.py
triton_dns_client.egg-info/PKG-INFO
triton_dns_client.egg-info/SOURCES.txt
triton_dns_client.egg-info/dependency_links.txt
triton_dns_client.egg-info/requires.txt
triton_dns_client.egg-info/top_level.txt