Metadata-Version: 2.1
Name: triton-dns-client
Version: 2019.10.13.2158
Summary: Async DNS client
Home-page: https://git.best-service.online/yurzs/triton
Author: Yury (Yurzs)
Author-email: dev@best-service.online
License: MIT
Keywords: triton,DNS,client
Platform: UNKNOWN
Classifier: Development Status :: 3 - Alpha
Classifier: Intended Audience :: Developers
Classifier: Topic :: Software Development :: Build Tools
Classifier: License :: OSI Approved :: MIT License
Classifier: Programming Language :: Python :: 3
Classifier: Programming Language :: Python :: 3.7
